<annotation>
	<folder>Hello</folder>
	<filename>Hello.155891c0-6aad-11eb-a6e2-ac11be106261.jpg</filename>
	<path>C:\D\Projects\MiniProject\Tensorflow\workspace\images\collectedimages\Hello\Hello.155891c0-6aad-11eb-a6e2-ac11be106261.jpg</path>
	<source>
		<database>Unknown</database>
	</source>
	<size>
		<width>640</width>
		<height>480</height>
		<depth>3</depth>
	</size>
	<segmented>0</segmented>
	<object>
		<name>Hello</name>
		<pose>Unspecified</pose>
		<truncated>0</truncated>
		<difficult>0</difficult>
		<bndbox>
			<xmin>190</xmin>
			<ymin>272</ymin>
			<xmax>317</xmax>
			<ymax>399</ymax>
		</bndbox>
	</object>
</annotation>
